docxcomtpl/__init__.py
docxcomtpl/com_utilities.py
docxcomtpl/docxcom_template.py
docxcomtpl-0.1.2.dist-info/licenses/LICENSE.MIT
docxcomtpl-0.1.2.dist-info/METADATA
docxcomtpl-0.1.2.dist-info/WHEEL
docxcomtpl-0.1.2.dist-info/top_level.txt
docxcomtpl-0.1.2.dist-info/RECORD
