Metadata-Version: 2.4
Name: docxcomtpl
Version: 0.1.2
Summary: A Python library that adds COM automation support for docx-template library
Author: KInside
License: Copyright 2025 Knowledge Inside
Classifier: License :: OSI Approved :: MIT License
Classifier: Programming Language :: Python :: 3
Requires-Python: >=3.8
License-File: LICENSE.MIT
Requires-Dist: pywin32
Requires-Dist: docxtpl
Dynamic: license-file
